autor/__init__.py
autor/_version.py
autor/file_parser.py
autor/finetune_llm.py
autor/llm_integrator.py
autor/main.py
autor/readme_parser.py
AutorGPT-0.1.1.dist-info/LICENSE
AutorGPT-0.1.1.dist-info/METADATA
AutorGPT-0.1.1.dist-info/WHEEL
AutorGPT-0.1.1.dist-info/entry_points.txt
AutorGPT-0.1.1.dist-info/top_level.txt
AutorGPT-0.1.1.dist-info/RECORD
