Metadata-Version: 2.1
Name: AutorGPT
Version: 0.1.1
Summary: A package for generating technical articles from project codebases using LLMs
Author: Elias Dzobo
Author-email: elias.dzobo@gmail.com
License: MIT
Classifier: License :: OSI Approved :: MIT License
Classifier: Programming Language :: Python :: 3
Classifier: Programming Language :: Python :: 3.7
Classifier: Programming Language :: Python :: 3.8
Classifier: Programming Language :: Python :: 3.9
Requires-Python: >=3.7
License-File: LICENSE
Requires-Dist: openai>=0.10.0
